restricted_paths/__init__.py
restricted_paths/middleware.py
restricted_paths-1.0.0.dist-info/METADATA
restricted_paths-1.0.0.dist-info/RECORD
restricted_paths-1.0.0.dist-info/WHEEL
restricted_paths-1.0.0.dist-info/top_level.txt
